ar_wordcloud/__init__.py
ar_wordcloud/_fonts.py
ar_wordcloud/ar_wordcloud.py
ar_wordcloud/stopwords
ar_wordcloud/utils.py
ar_wordcloud-0.0.4.dist-info/WHEEL
ar_wordcloud-0.0.4.dist-info/METADATA
ar_wordcloud-0.0.4.dist-info/RECORD
