Metadata-Version: 2.1
Name: ar_wordcloud
Version: 0.0.4
Summary: A tiny wrapper around `wordcloud.WordCloud` to support Arabic WordCloud
Home-page: https://github.com/iamaziz/ar_wordcloud
License: UNKNOWN
Author: Aziz Alto
Author-email: iamaziz.alto@gmail.com
Requires-Python: >=3.4
Classifier: License :: OSI Approved :: MIT License
Requires-Dist: requests
Requires-Dist: wordcloud >=1.7.0
Requires-Dist: python-bidi >=0.4.2
Requires-Dist: arabic_reshaper >=2.0.14
